vulnerabilitylookupsighting/conf_sample.py
vulnerabilitylookupsighting/config.py
vulnerabilitylookupsighting/publish.py
vulnerabilitylookupsighting-0.4.1.dist-info/COPYING
vulnerabilitylookupsighting-0.4.1.dist-info/METADATA
vulnerabilitylookupsighting-0.4.1.dist-info/WHEEL
vulnerabilitylookupsighting-0.4.1.dist-info/entry_points.txt
vulnerabilitylookupsighting-0.4.1.dist-info/RECORD
