Metadata-Version: 2.1
Name: VulnerabilityLookupSighting
Version: 0.4.1
Summary: A client that retrieves vulnerability observations from a MISP server and pushes them to a Vulnerability Lookup instance.
Home-page: https://github.com/MISP/VulnerabilityLookupSighting
License: GPL-3.0-or-later
Keywords: vulnerability,cve,sighting,observations,MISP,PyVulnerabilityLookup
Author: Cédric Bonhomme
Author-email: cedric@cedricbonhomme.org
Requires-Python: >=3.10,<4.0
Classifier: Development Status :: 5 - Production/Stable
Classifier: Environment :: Console
Classifier: Intended Audience :: Developers
Classifier: Intended Audience :: Science/Research
Classifier: License :: OSI Approved :: GNU General Public License v3 or later (GPLv3+)
Classifier: Operating System :: POSIX :: Linux
Classifier: Programming Language :: Python :: 3
Classifier: Programming Language :: Python :: 3.10
Classifier: Programming Language :: Python :: 3.11
Classifier: Programming Language :: Python :: 3.12
Classifier: Programming Language :: Python :: 3.13
Classifier: Topic :: Security
Requires-Dist: pymisp (>=2.5.2,<3.0.0)
Requires-Dist: pyvulnerabilitylookup (>=2.1.0,<3.0.0)
Project-URL: Repository, https://github.com/MISP/VulnerabilityLookupSighting
